setup.py
Douwa_Meta.egg-info/PKG-INFO
Douwa_Meta.egg-info/SOURCES.txt
Douwa_Meta.egg-info/dependency_links.txt
Douwa_Meta.egg-info/not-zip-safe
Douwa_Meta.egg-info/top_level.txt
douwa_meta/__init__.py
douwa_meta/douwa_meta.py