Metadata-Version: 1.1
Name: Douwa-Meta
Version: 0.0.5
Summary: 一个flask插件,meta,type的生成预校验
Home-page: UNKNOWN
Author: jjq
Author-email: woshijiangjinqi@163.com
License: MIT
Platform: any
Classifier: Framework :: Flask
Classifier: Natural Language :: English
Classifier: Environment :: Web Environment
Classifier: Intended Audience :: Developers
Classifier: License :: OSI Approved :: MIT License
Classifier: Operating System :: OS Independent
Classifier: Programming Language :: Python
Classifier: Topic :: Internet :: WWW/HTTP :: Dynamic Content
Classifier: Topic :: Software Development :: Libraries :: Python Modules
